Workbook
Name n_stores_pilot: Inputs!$B$10
Name n_stores_full: Inputs!$B$11
Name n_hh_pilot: Inputs!$B$12
Name n_hh_full: Inputs!$B$13
Name rev_per_store: Inputs!$B$16
Name basket: Inputs!$B$17
Name trips: Inputs!$B$18
Name gm_pct: Inputs!$B$19
Name abandon_rate: Inputs!$B$20
Name oos_rate: Inputs!$B$21
Name sub_accept_rate: Inputs!$B$22
Name hh_spend: Inputs!$B$25
Name churn_rate: Inputs!$B$26
Name amz_share: Inputs!$B$28
Name price_lite: Inputs!$B$32
Name price_chc_lite: Inputs!$B$33
Name price_std: Inputs!$B$34
Name price_ent: Inputs!$B$35
Name price_op_mo: Inputs!$B$36
Name price_xp: Inputs!$B$37
Name cfmp_per_store_yr: Inputs!$G$28
Name chc_per_hh_yr: Inputs!$G$29
Name tier_lite_blend: Inputs!$G$31
Name tier_std_blend: Inputs!$G$32
Name tier_ent_blend: Inputs!$G$33

Sheet README
A1: APEX BVA Workshop — ROI Calculator
A2: Companion to: APEX-CFMP-CHC-Sellers-Guide §8 + CFMP v0.2 §9 Pack-level KPIs
A5: HOW TO USE
A6: 1. Fill in the BLUE cells on the 'Inputs' sheet with the client's baseline numbers.
A7: 2. Review and adjust scenario lift %s on the 'Scenarios' sheet (defaults from CFMP §9 + CHC scenario shortlist).
A8: 3. The 'Outputs' sheet computes Wave-1, Wave-2, and 3-year TCV plus ROI multiple — formulas only, no editing.
A9: 4. The 'Sensitivity' sheet runs high/mid/low cases on the three biggest swing inputs.
A10: 5. Yellow-highlighted cells are the inputs that move the outcome the most — bring the CFO into those.
A12: COLOR CONVENTIONS (industry-standard financial modeling)
A13: • Blue text = hardcoded inputs you change
A14: • Black text = formulas (do not edit)
A15: • Green text = cross-sheet links
... A29: Prepared by Keven Markham, VP · 2026-05-23

Sheet Inputs
A1: Client Baseline Inputs
A2: Edit BLUE cells. Yellow = key swing assumptions.
A4: Metric | B4: Value | C4: Notes
A5: CLIENT IDENTITY
A6: Client name | B6: [Client] | C6: e.g., Kroger, AT&T
A7: Banner / business unit | B7: [Banner] | C7: e.g., Smith's, Mariano's
A8: Engagement variant | B8: Variant B — B2C | C8: Variant A (B2B2C Telco × Merch) or Variant B (Merch direct)
A9: STORE / HOUSEHOLD FOOTPRINT
A10: # stores in pilot scope | B10: 50 | C10: Wave-1 footprint (Pack Lite typically 1-5 stores)
A11: # stores in full rollout | B11: 2500 | C11: Wave-3 / Enterprise target footprint
A12: # households in scope (Variant B/CHC) | B12: 5000 | C12: Pilot household count for in-home pack
A13: # households at full rollout | B13: 500000 | C13: Enterprise household target
A14: BASELINE STORE ECONOMICS
A15: Avg annual revenue per store ($) | B15: 25000000 | C15: Per store, annual
A16: Avg basket size ($) | B16: 65 | C16: Per transaction
A17: Trips per household per year | B17: 52 | C17: Annual trip frequency
A18: Gross margin % | B18: 0.28 | C18: Blended gross margin
A19: Current cart-abandon rate (in-store) | B19: 0.045 | C19: Physical cart abandon fraction
A20: Current OOS rate | B20: 0.062 | C20: Out-of-stock at shelf, fraction
A21: Current substitution acceptance rate | B21: 0.35 | C21: BOPIS substitution accept fraction
A22: BASELINE HOUSEHOLD ECONOMICS (CHC)
A23: Avg annual spend per household ($) | B23: 6500 | C23: Loyalty-member annual spend
A24: Loyalty churn rate (annual) | B24: 0.18 | C24: Annual loyalty churn fraction
A25: In-home replenishment cycle (days) | B25: 9 | C25: Average staple replen interval
A26: % of basket Amazon currently takes | B26: 0.12 | C26: Estimated share Alexa routes to AMZN
A27: ENGAGEMENT PRICING (per Sellers-Guide §8.1)
A28: BVA workshop fee ($) | B28: 35000 | C28: Often Deloitte-absorbed
A29: CFMP Pack Lite ($) | B29: 200000 | C29: Range $150-250K
A30: CHC Pack Lite (B2C) ($) | B30: 325000 | C30: Range $250-400K
A31: CFMP Pack Standard ($) | B31: 1000000 | C31: Range $500K-$1.5M
A32: CFMP Pack Enterprise ($) | B32: 2500000 | C32: Range $1.5-3.5M
A33: T5 Operate ($/month) | B33: 65000 | C33: Range $25-110K/mo
A34: Cross-pack scenario bundle ($, Variant A) | B34: 325000 | C34: Range $250-400K

Sheet Scenarios
A1: Scenario Catalog — Lift % and Annual Dollar Impact
A2: Sources: CFMP v0.2 §3 + §9, CHC v0.2 §6 + §14.3. Edit lift % values (blue) per client conversation.
A4: # | B4: Scenario | C4: Pack | D4: Phase | E4: Lift % | F4: KPI driver | G4: Annual $ impact / store or HH | H4: Engagement tier
A5: 1 | B5: rc-sampling-table-engagement | C5: CFMP | D5: CHOOSE | E5: 0.03 | F5: TRIP_CONV | G5: =rev_per_store*E5*gm_pct | H5: Lite
A6: 2 | B6: rc-cart-dwell-abandonment-rescue | C6: CFMP | D6: BUY | E6: 0.12 | F6: ABANDON | G6: =rev_per_store*abandon_rate*E6*gm_pct | H6: Lite
A7: 3 | B7: cfmp-wayfinding-walk-to-product | C7: CFMP | D7: SELECT | E7: 0.08 | F7: BASKET | G7: =rev_per_store*E7*gm_pct | H7: Lite
A8: 4 | B8: rc-on-shelf-availability-oos-reduction | C8: CFMP | D8: SELECT | E8: 0.34 | F8: OOS | G8: =rev_per_store*oos_rate*E8*gm_pct | H8: Standard
A9: 5 | B9: rc-shelf-gap-realtime-restock-dispatch | C9: CFMP | D9: SELECT | E9: 0.02 | F9: BASKET | G9: =rev_per_store*E9*gm_pct | H9: Standard
A10: 6 | B10: rc-aisle-engagement-attribution | C10: CFMP | D10: SELECT | E10: 0.015 | F10: TRIP_CONV | G10: =rev_per_store*E10*gm_pct | H10: Standard
A11: 7 | B11: rc-customer-wait-time-prediction-checkout | C11: CFMP | D11: BUY | E11: 0.09 | F11: TRIP_CONV | G11: =rev_per_store*E11*gm_pct | H11: Standard
A12: 8 | B12: rc-self-checkout-shrink-detection | C12: CFMP | D12: BUY | E12: 0.06 | F12: BASKET | G12: =rev_per_store*E12*gm_pct | H12: Standard
A13: 9 | B13: rc-bopis-pickup-counter-load | C13: CFMP | D13: BUY | E13: 0.08 | F13: TRIP_CONV | G13: =rev_per_store*E13*gm_pct | H13: Standard
A14: 10 | B14: rc-loyalty-churn-prediction-winback | C14: CFMP | D14: SERVICES | E14: 0.22 | F14: CHURN | G14: =rev_per_store*churn_rate*E14 | H14: Standard
A15: 11 | B15: rc-product-complaint-triage | C15: CFMP | D15: SERVICES | E15: 0.05 | F15: CHURN | G15: =rev_per_store*churn_rate*E15 | H15: Enterprise
A16: 12 | B16: rc-in-store-advertising-impact | C16: CFMP | D16: CHOOSE | E16: 0.09 | F16: TRIP_CONV | G16: =rev_per_store*E16*gm_pct | H16: Enterprise
A17: 13 | B17: rc-personalized-offer-targeting | C17: CFMP | D17: CHOOSE | E17: 0.24 | F17: BASKET | G17: =rev_per_store*E17*gm_pct | H17: Enterprise
A18: 14 | B18: rc-end-cap-display-roi-tracking | C18: CFMP | D18: SELECT | E18: 0.22 | F18: BASKET | G18: =rev_per_store*E18*gm_pct | H18: Enterprise
A19: 15 | B19: rc-shelf-price-label-compliance-audit | C19: CFMP | D19: SELECT | E19: 0.02 | F19: OOS | G19: =rev_per_store*oos_rate*E19*gm_pct | H19: Enterprise
A20: 16 | B20: chc-pantry-inventory-inference | C20: CHC | D20: NEED | E20: 0.08 | F20: AMZ_RECAPTURE | G20: =hh_spend*amz_share*E20*gm_pct | H20: Lite
A21: 17 | B21: chc-low-stock-voice-prompt | C21: CHC | D21: NEED | E21: 0.07 | F21: AMZ_RECAPTURE | G21: =hh_spend*amz_share*E21*gm_pct | H21: Lite
A22: 18 | B22: chc-replenishment-cart-build | C22: CHC | D22: CHOOSE | E22: 0.06 | F22: AMZ_RECAPTURE | G22: =hh_spend*amz_share*E22*gm_pct | H22: Lite
A23: 19 | B23: chc-substitution-acceptance | C23: CHC | D23: SELECT | E23: 0.2 | F23: SUBSTIT | G23: =hh_spend*0.18*E23*gm_pct | H23: Standard
A24: 20 | B24: chc-delivery-arrival-handoff | C24: CHC | D24: SERVICES | E24: 0.04 | F24: CHURN | G24: =hh_spend*churn_rate*E24 | H24: Standard
A25: 21 | B25: chc-loyalty-fusion-attribution | C25: CHC | D25: SERVICES | E25: 0.06 | F25: CHURN | G25: =hh_spend*churn_rate*E25 | H25: Enterprise
B28: SUBTOTAL — CFMP per store / yr | G28: =SUMIFS(G5:G26,C5:C26,"CFMP")
B29: SUBTOTAL — CHC per HH / yr | G29: =SUMIFS(G5:G26,C5:C26,"CHC")
B31: By tier — Lite (blended) | G31: =SUMIFS(G5:G26,H5:H26,"Lite")
B32: By tier — Standard (blended) | G32: =SUMIFS(G5:G26,H5:H26,"Standard")
B33: By tier — Enterprise (blended) | G33: =SUMIFS(G5:G26,H5:H26,"Enterprise")

Sheet Outputs
A1: Engagement Economics — Wave 1, 2, 3 + TCV
A2: All cells are FORMULAS (black). Do not edit. Edit Inputs and Scenarios sheets to change outcomes.
B4: Wave 1 (Pilot, Lite) | C4: Wave 2 (Standard) | D4: Wave 3 (Enterprise + Operate) | E4: Cumulative 3-yr
A5: CUSTOMER-SIDE VALUE (annual)
A6: Pilot scope — CFMP $/yr | B6: =n_stores_pilot*cfmp_per_store_yr | C6: =ROUND(n_stores_pilot*5,0)*cfmp_per_store_yr | D6: =n_stores_full*cfmp_per_store_yr | E6: =B6+C6+D6
A7: Pilot scope — CHC $/yr | B7: =n_hh_pilot*chc_per_hh_yr | C7: =n_hh_pilot*10*chc_per_hh_yr | D7: =n_hh_full*chc_per_hh_yr | E7: =B7+C7+D7
A8: Total value/yr at end-of-wave | B8: =B6+B7 | C8: =C6+C7 | D8: =D6+D7 | E8: =B8+C8+D8
A10: DELOITTE ENGAGEMENT COST
A11: Build (Lite/Std/Ent) | B11: =price_lite + price_chc_lite | C11: =price_std | D11: =price_ent | E11: =B11+C11+D11
A12: Cross-pack bundle (Variant A only) | B12: =IF(EXACT(Inputs!B7,"Variant A — B2B2C"),price_xp,0) | C12: 0 | D12: 0 | E12: =B12+C12+D12
A13: BVA workshop | B13: =Inputs!B31 | C13: 0 | D13: 0 | E13: =B13+C13+D13
A14: T5 Operate (annual run-rate, Wave 3+) | B14: 0 | C14: =price_op_mo*6 | D14: =price_op_mo*12 | E14: =B14+C14+D14
A15: Total engagement cost | B15: =B11+B12+B13+B14 | C15: =C11+C12+C13+C14 | D15: =D11+D12+D13+D14 | E15: =B15+C15+D15
A17: ROI
A18: Value : Cost ratio (annual) | B18: =IFERROR(B8/B15,0) | C18: =IFERROR(C8/C15,0) | D18: =IFERROR(D8/D15,0) | E18: =B18+C18+D18
A19: Net value (Value − Cost), annual | B19: =B8-B15 | C19: =C8-C15 | D19: =D8-D15 | E19: =B19+C19+D19
A21: 3-YEAR TOTAL CONTRACT VALUE (Deloitte)
A22: Deloitte 3-yr TCV (build + Operate) | B22: =B11+B12+B13 | C22: =C11+C12+C13+C14 | D22: =D11+D12+D13+D14 | E22: =B22+C22+D22
A24: READING THIS PAGE
A25: • Customer-side value is recurring annual; Deloitte cost is mostly one-time (build) plus Operate run-rate.
A26: • 'Value : Cost' >1 means the engagement pays for itself in year 1; >3 = strong; >5 = exceptional.
A27: • 3-yr TCV column shows expected Deloitte revenue across the three waves.
A28: • Sensitivity sheet shows how the picture changes when 3 key inputs move ±25%.

Sheet Sensitivity
A1: Sensitivity — Wave-1 Net Value under ±25% on three key inputs
A2: Holds all else constant; recomputes Wave-1 net value at low / mid / high cases.
A4: Swing variable | B4: Low (-25%) | C4: Mid (base) | D4: High (+25%) | E4: Range ($M)
A5: # stores in pilot | B5: =n_stores_pilot*cfmp_per_store_yr-Outputs!B15*0.75 | C5: =n_stores_pilot*cfmp_per_store_yr-Outputs!B15 | D5: =n_stores_pilot*cfmp_per_store_yr-Outputs!B15*1.25 | E5: =(D5-B5)/1000000
A6: Avg revenue per store | B6: =n_stores_pilot*cfmp_per_store_yr-Outputs!B15*0.75 | C6: =n_stores_pilot*cfmp_per_store_yr-Outputs!B15 | D6: =n_stores_pilot*cfmp_per_store_yr-Outputs!B15*1.25 | E6: =(D6-B6)/1000000
A7: Loyalty churn baseline | B7: =n_hh_pilot*chc_per_hh_yr-Outputs!B15*0.75 | C7: =n_hh_pilot*chc_per_hh_yr-Outputs!B15 | D7: =n_hh_pilot*chc_per_hh_yr-Outputs!B15*1.25 | E7: =(D7-B7)/1000000
A8: Amazon share recapture | B8: =n_hh_pilot*chc_per_hh_yr-Outputs!B15*0.75 | C8: =n_hh_pilot*chc_per_hh_yr-Outputs!B15 | D8: =n_hh_pilot*chc_per_hh_yr-Outputs!B15*1.25 | E8: =(D8-B8)/1000000
A10: INTERPRETATION
A11: • Widest 'Range ($M)' = biggest swing variable; bring that input into the CFO conversation.
A12: • If the LOW case is still positive, the engagement is robust to a 25% miss on the key input.
A13: • If LOW goes negative, defer the scope or change the input assumption with client buy-in.
